postman2openapi/__init__.py
postman2openapi/converter.py
postman2openapi/utils.py
postman2openapi-1.0.1.dist-info/licenses/LICENSE
tests/__init__.py
tests/test_converter.py
tests/test_utils.py
postman2openapi-1.0.1.dist-info/METADATA
postman2openapi-1.0.1.dist-info/WHEEL
postman2openapi-1.0.1.dist-info/top_level.txt
postman2openapi-1.0.1.dist-info/RECORD
