Metadata-Version: 2.4
Name: postman2openapi
Version: 1.0.1
Summary: Convert Postman Collections to OpenAPI (Swagger) specification
Home-page: https://github.com/Pulkit-Py/postman2openapi
Author: Pulkit-Py
Author-email: your.email@example.com
Project-URL: Bug Tracker, https://github.com/Pulkit-Py/postman2openapi/issues
Project-URL: Documentation, https://github.com/Pulkit-Py/postman2openapi#readme
Project-URL: Source Code, https://github.com/Pulkit-Py/postman2openapi
Keywords: postman,openapi,swagger,api,converter,documentation,rest,api-documentation,postman-collection,openapi-specification
Classifier: Programming Language :: Python :: 3
Classifier: Programming Language :: Python :: 3.7
Classifier: Programming Language :: Python :: 3.8
Classifier: Programming Language :: Python :: 3.9
Classifier: Programming Language :: Python :: 3.10
Classifier: Programming Language :: Python :: 3.11
Classifier: License :: OSI Approved :: MIT License
Classifier: Operating System :: OS Independent
Classifier: Development Status :: 4 - Beta
Classifier: Intended Audience :: Developers
Classifier: Topic :: Software Development :: Libraries :: Python Modules
Classifier: Topic :: Software Development :: Documentation
Classifier: Topic :: Internet :: WWW/HTTP :: Dynamic Content
Requires-Python: >=3.7
License-File: LICENSE
Requires-Dist: pyyaml>=5.1
Provides-Extra: dev
Requires-Dist: pytest>=6.0; extra == "dev"
Requires-Dist: pytest-cov>=2.0; extra == "dev"
Requires-Dist: black>=22.0; extra == "dev"
Requires-Dist: isort>=5.0; extra == "dev"
Requires-Dist: flake8>=3.9; extra == "dev"
Dynamic: author
Dynamic: author-email
Dynamic: classifier
Dynamic: description
Dynamic: description-content-type
Dynamic: home-page
Dynamic: keywords
Dynamic: license-file
Dynamic: project-url
Dynamic: provides-extra
Dynamic: requires-dist
Dynamic: requires-python
Dynamic: summary
